SarnAi/__init__.py
SarnAi/functions.py
SarnAi/layers.py
SarnAi/memory.py
SarnAi/network.py
SarnAi/utils.py
sarn-0.1.1.dist-info/LICENSE
sarn-0.1.1.dist-info/METADATA
sarn-0.1.1.dist-info/WHEEL
sarn-0.1.1.dist-info/top_level.txt
sarn-0.1.1.dist-info/RECORD
