Metadata-Version: 2.1
Name: sarn
Version: 0.1.1
Summary: SARN - Self-Adaptive Rewiring Neural Network
Home-page: https://github.com/Iro96/SarnAI
Author: Iro Sowara
Author-email: bruh8080p@gmail.com
Classifier: Programming Language :: Python :: 3
Classifier: License :: OSI Approved :: Apache Software License
Classifier: Operating System :: OS Independent
Classifier: Topic :: Scientific/Engineering :: Artificial Intelligence
Requires-Python: >=3.8
License-File: LICENSE
Requires-Dist: numpy
